setup.py
plytype/__init__.py
plytype/cpp.py
plytype/ctokens.py
plytype/lex.py
plytype/yacc.py
plytype/ygen.py
plytype.egg-info/PKG-INFO
plytype.egg-info/SOURCES.txt
plytype.egg-info/dependency_links.txt
plytype.egg-info/top_level.txt